{
  "product": [
    {
      "id": "1",
      "name": "HP Victus Gaming Laptop, 12th Gen Intel Core i5-12450H, 4GB RTX 3050 GPU, 15.6-inch (39.6 cm) FHD IPS 144Hz, 16GB DDR4, 512GB SSD",
      "price": 67999,
      "quantity": 1,
      "imageUrl": "https://images.unsplash.com/photo-1588872657840-90a4cd5b422b?w=500&h=500&fit=crop",
      "rating": 4.5,
      "reviews": 245
    },
    {
      "id": "2",
      "name": "boAt Airdopes 141 Bluetooth TWS Earbuds with 42H Playtime, Low Latency Mode for Gaming, ENx Tech, IWP, IPX4 Water Resistance",
      "price": 1299,
      "quantity": 1,
      "imageUrl": "https://images.unsplash.com/photo-1505740420928-5e560c06d30e?w=500&h=500&fit=crop",
      "rating": 4.2,
      "reviews": 512
    },
    {
      "id": "3",
      "name": "boAt Immortal 121 in Ear TWS Earbuds with Beast Mode 40ms Low Latency for Gaming, 40H Playtime, Blazing LEDs, Quad Mics",
      "price": 999,
      "quantity": 1,
      "imageUrl": "https://images.unsplash.com/photo-1484704849700-f032a568e944?w=500&h=500&fit=crop",
      "rating": 4.3,
      "reviews": 389
    },
    {
      "id": "4",
      "name": "iPhone 15 Pro Max, 256GB, Natural Titanium - Unlocked",
      "price": 119999,
      "quantity": 1,
      "imageUrl": "https://images.unsplash.com/photo-1592286927505-1def25115558?w=500&h=500&fit=crop",
      "rating": 4.7,
      "reviews": 1023
    },
    {
      "id": "5",
      "name": "Xiaomi Pad 6 | Qualcomm Snapdragon 870 | Powered by HyperOS | 144Hz Refresh Rate | 6GB RAM, 128GB Storage | 2.8K+ Display",
      "price": 24999,
      "quantity": 1,
      "imageUrl": "https://images.unsplash.com/photo-1561070791-2526d30994b5?w=500&h=500&fit=crop",
      "rating": 4.4,
      "reviews": 678
    },
    {
      "id": "6",
      "name": "Samsung Galaxy S23 Ultra, 12GB RAM, 256GB Storage, 200MP Camera, 6.8-inch AMOLED Display, Phantom Black",
      "price": 174999,
      "quantity": 1,
      "imageUrl": "https://images.unsplash.com/photo-1511707267537-b85faf00021e?w=500&h=500&fit=crop",
      "rating": 4.6,
      "reviews": 834
    },
    {
      "id": "7",
      "name": "Apple MacBook Air M2, 13.6-inch Retina Display, 8GB RAM, 256GB SSD, Silver",
      "price": 139999,
      "quantity": 1,
      "imageUrl": "https://images.unsplash.com/photo-1517336714731-489689fd1ca8?w=500&h=500&fit=crop",
      "rating": 4.8,
      "reviews": 456
    },
    {
      "id": "8",
      "name": "Dell XPS 13 Plus Laptop, Intel Core Ultra 5 135U, 16GB RAM, 512GB SSD, 13.3-inch 3K+ OLED Display, Umber",
      "price": 124999,
      "quantity": 1,
      "imageUrl": "https://images.unsplash.com/photo-1527864550417-7fd91fc51a46?w=500&h=500&fit=crop",
      "rating": 4.5,
      "reviews": 234
    },
    {
      "id": "9",
      "name": "Lenovo ThinkPad X1 Carbon Gen 11, Intel Core i7-1365U, 16GB RAM, 512GB SSD, 14-inch FHD IPS Touch, Business Black",
      "price": 159999,
      "quantity": 1,
      "imageUrl": "https://images.unsplash.com/photo-1588872657840-90a4cd5b422b?w=500&h=500&fit=crop",
      "rating": 4.4,
      "reviews": 567
    },
    {
      "id": "10",
      "name": "ASUS ROG Zephyrus G14, RTX 4060, Intel Core i9-13900H, 16GB RAM, 1TB SSD, 14-inch QHD+ 165Hz, Eclipse Gray",
      "price": 189999,
      "quantity": 1,
      "imageUrl": "https://images.unsplash.com/photo-1595225476942-2b745ecc3d60?w=500&h=500&fit=crop",
      "rating": 4.7,
      "reviews": 345
    },
    {
      "id": "11",
      "name": "Sony WH-CH720 Wireless Headphones, 35-hour battery life, Lightweight Design, Black",
      "price": 4999,
      "quantity": 1,
      "imageUrl": "https://images.unsplash.com/photo-1505740420928-5e560c06d30e?w=500&h=500&fit=crop",
      "rating": 4.3,
      "reviews": 612
    },
    {
      "id": "12",
      "name": "Samsung 32-inch M7 Smart Monitor 4K, 60Hz Refresh Rate, Built-in Speakers, Remote Control Included",
      "price": 49999,
      "quantity": 1,
      "imageUrl": "https://images.unsplash.com/photo-1593642632823-8f785ba67e45?w=500&h=500&fit=crop",
      "rating": 4.5,
      "reviews": 289
    }
  ]
}
